setup.py
simple_server/__init__.py
simple_server.egg-info/PKG-INFO
simple_server.egg-info/SOURCES.txt
simple_server.egg-info/dependency_links.txt
simple_server.egg-info/entry_points.txt
simple_server.egg-info/top_level.txt