Metadata-Version: 1.0
Name: simple-server
Version: v0.1.1
Summary: A Python version-independent HTTP server.
Home-page: https://github.com/brianhou/fuzzy-octo-ironman
Author: Brian Hou
Author-email: UNKNOWN
License: UNKNOWN
Platform: UNKNOWN
